dataqueryframe/__init__.py
dataqueryframe/dataqueryframe.py
dataqueryframe-0.1.0.dist-info/AUTHORS.rst
dataqueryframe-0.1.0.dist-info/LICENSE
dataqueryframe-0.1.0.dist-info/METADATA
dataqueryframe-0.1.0.dist-info/WHEEL
dataqueryframe-0.1.0.dist-info/top_level.txt
dataqueryframe-0.1.0.dist-info/RECORD
