Metadata-Version: 2.1
Name: dataqueryframe
Version: 0.1.0
Summary: An enhanced DataFrame with SQL-like capabilities.
Home-page: https://github.com/jmccoll7/dataqueryframe
Author: James McColl
Author-email: jmccoll71@gmail.com
License: MIT license
Keywords: dataqueryframe
Classifier: Development Status :: 2 - Pre-Alpha
Classifier: Intended Audience :: Developers
Classifier: License :: OSI Approved :: MIT License
Classifier: Natural Language :: English
Classifier: Programming Language :: Python :: 3
Classifier: Programming Language :: Python :: 3.6
Classifier: Programming Language :: Python :: 3.7
Classifier: Programming Language :: Python :: 3.8
Requires-Python: >=3.6
License-File: LICENSE
License-File: AUTHORS.rst
